qsharp_lang-1.0.29.dev0.dist-info/METADATA
qsharp_lang-1.0.29.dev0.dist-info/WHEEL
qsharp/.data/qsharp_codemirror.js
qsharp/estimator/_estimator.py
qsharp/estimator/__init__.py
qsharp/_fs.py
qsharp/_ipython.py
qsharp/_native.pyi
qsharp/_qsharp.py
qsharp/__init__.py
qsharp/_native.pyd
qsharp_lang-1.0.29.dev0.dist-info/RECORD
