Metadata-Version: 2.1
Name: qsharp-lang
Version: 1.0.29.dev0
Classifier: License :: OSI Approved :: MIT License
Classifier: Development Status :: 3 - Alpha
Classifier: Intended Audience :: Developers
Classifier: Programming Language :: Python :: 3.7
Classifier: Programming Language :: Python :: 3.8
Classifier: Programming Language :: Python :: 3.9
Classifier: Programming Language :: Python :: 3.10
Classifier: Programming Language :: Python :: 3.11
Classifier: Programming Language :: Python
Classifier: Programming Language :: Rust
Classifier: Operating System :: MacOS
Classifier: Operating System :: Microsoft :: Windows
Classifier: Operating System :: POSIX :: Linux
Requires-Dist: qsharp-jupyterlab ; extra == 'jupyterlab'
Requires-Dist: qsharp-widgets ; extra == 'widgets'
Provides-Extra: jupyterlab
Provides-Extra: widgets
Summary: Q# Python Bindings
Home-Page: https://github.com/microsoft/qsharp
Author: Microsoft
License: MIT
Requires-Python: >=3.7
Project-URL: Source Code, https://github.com/microsoft/qsharp
